uipath_connectors/sap_bapi/__init__.py
uipath_connectors/sap_bapi/client.py
uipath_connectors/sap_bapi/errors.py
uipath_connectors/sap_bapi/py.typed
uipath_connectors/sap_bapi/types.py
uipath_connectors/sap_bapi/api/__init__.py
uipath_connectors/sap_bapi/api/bapisexecute/__init__.py
uipath_connectors/sap_bapi/api/bapisexecute/execute_bapi.py
uipath_connectors/sap_bapi/models/__init__.py
uipath_connectors/sap_bapi/models/default_error.py
uipath_connectors_sap_bapi-1.1.0.dev12.dist-info/METADATA
uipath_connectors_sap_bapi-1.1.0.dev12.dist-info/WHEEL
uipath_connectors_sap_bapi-1.1.0.dev12.dist-info/entry_points.txt
uipath_connectors_sap_bapi-1.1.0.dev12.dist-info/top_level.txt
uipath_connectors_sap_bapi-1.1.0.dev12.dist-info/RECORD
